django_gofastdfs_storage/__init__.py
django_gofastdfs_storage/backends.py
django_gofastdfs_storage-1.0.4.dist-info/LICENSE
django_gofastdfs_storage-1.0.4.dist-info/METADATA
django_gofastdfs_storage-1.0.4.dist-info/WHEEL
django_gofastdfs_storage-1.0.4.dist-info/top_level.txt
django_gofastdfs_storage-1.0.4.dist-info/RECORD
