Metadata-Version: 2.1
Name: django-gofastdfs-storage
Version: 1.0.4
Summary: Django storage backends for go-fastdfs
Home-page: https://github.com/lsdlab/django-gofastdfs-storage
Author: JC
Author-email: lsdvincent@gmail.com
Maintainer: JC
Maintainer-email: lsdvincent@gmail.com
License: MIT
Platform: UNKNOWN
Classifier: Development Status :: 5 - Production/Stable
Classifier: Intended Audience :: Developers
Classifier: License :: OSI Approved :: MIT License
Classifier: Operating System :: OS Independent
Classifier: Programming Language :: Python
Classifier: Programming Language :: Python :: 3
Classifier: Programming Language :: Python :: 3.3
Classifier: Programming Language :: Python :: 3.4
Classifier: Programming Language :: Python :: 3.5
Classifier: Programming Language :: Python :: 3.6
Classifier: Programming Language :: Python :: 3.7
Classifier: Programming Language :: Python :: 3.8
Classifier: Programming Language :: Python :: 3.9
Classifier: Framework :: Django
License-File: LICENSE
Requires-Dist: django (>=2.1.10)
Requires-Dist: requests (>=2.26.0)
